odoo/addons/pos_hide_partner_info/README.rst
odoo/addons/pos_hide_partner_info/__init__.py
odoo/addons/pos_hide_partner_info/__manifest__.py
odoo/addons/pos_hide_partner_info/i18n/pos_hide_partner_info.pot
odoo/addons/pos_hide_partner_info/readme/CONTRIBUTORS.rst
odoo/addons/pos_hide_partner_info/readme/DESCRIPTION.rst
odoo/addons/pos_hide_partner_info/static/description/icon.png
odoo/addons/pos_hide_partner_info/static/description/index.html
odoo/addons/pos_hide_partner_info/static/src/xml/templates.xml
odoo12_addon_pos_hide_partner_info-12.0.2.0.1.dist-info/METADATA
odoo12_addon_pos_hide_partner_info-12.0.2.0.1.dist-info/WHEEL
odoo12_addon_pos_hide_partner_info-12.0.2.0.1.dist-info/top_level.txt
odoo12_addon_pos_hide_partner_info-12.0.2.0.1.dist-info/RECORD
